{"ID": 891, "Provider": "businessinsider", "URL": "https://businessinsider.com.pl/praca/emerytury/emerytury-kobiet-z-rocznika-1953-prace-w-senacie/hecf10v", "Zdarzenie": "Inicjatywa Senatu dotycząca przeliczenia emerytur dla kobiet z rocznika 1953.", "Temat": "Sprawiedliwość społeczna i zmiany w prawie emerytalnym.", "Długość": "Krótki artykuł informacyjny.", "Wygenerowany tytuł": "Senat proponuje przeliczenie emerytur dla kobiet urodzonych w 1953 r. – krok w kierunku sprawiedliwości społecznej  \n\n", "Wygenerowany tekst": "  \nSenat Rzeczypospolitej Polskiej podjął inicjatywę mającą na celu przeliczenie świadczeń emerytalnych dla kobiet z rocznika 1953. Projekt zakłada uwzględnienie okresów opieki nad dziećmi oraz pracy w zawodach o podwyższonym ryzyku, które dotychczas nie były w pełni brany pod uwagę przy wyliczaniu wysokości emerytury. Autorzy zmiany podkreślają, że celem jest zniwelowanie dysproporcji między świadczeniami kobiet a mężczyzn oraz zapewnienie godnej starości osobom, które przez lata poświęcały się rodzinie i zawodom wymagającym szczególnego zaangażowania. Proponowane przepisy mają trafić do dalszych prac legislacyjnych w Sejmie, a ich przyjęcie mogłoby stanowić istotny krok w reformie systemu emerytalnego w kierunku większej sprawiedliwości społecznej. W przypadku pozytywnego rozpatrzenia projektu, pierwsze podwyższone świadczenia mogłyby zostać wypłacone już w nadchodzącym roku budżetowym.", "Model": "@cf/nvidia/nemotron-3-120b-a12b"}