{"ID": 2225, "Provider": "tvp", "URL": "https://www.tvp.info/19682205/z-opuszczonymi-do-kolan-spodniami-prowokowal-na-ulicy-zmarl-po-zazyciu-kosiarza", "Zdarzenie": "Śmierć 28-latka w Katowicach po interwencji policji, prawdopodobnie po zażyciu dopalaczy.", "Temat": "Zagrożenia związane z zażywaniem środków odurzających i interwencja służb.", "Długość": "Średniej długości artykuł informacyjny.", "Wygenerowany tytuł": "Śmierć 28-latka w Katowicach po interwencji policji - zagrożenia związane z zażywaniem dopalaczy\n\n", "Wygenerowany tekst": " W Katowicach doszło do tragicznego zdarzenia, w którym 28-letni mężczyzna zmarł po interwencji policji, prawdopodobnie związanym z zażyciem dopalaczy. Ten wstrząsający incydent ponownie zwrócił uwagę na niebezpieczeństwa związane z zażywaniem środków odurzających, które mogą mieć tragiczne konsekwencje dla zdrowia i życia osób nimi uzależnionych.\n\nDopalacze, czyli syntetyczne substancje psychoaktywne, są niezwykle niebezpieczne ze względu na swoją nieprzewidywalność i brak badań nad ich długoterminowym wpływem na organizm ludzki. Mogą powodować zaburzenia psychiczne, problemy sercowo-naczyniowe, a nawet prowadzić do zgonu. Niestety, wielu młodych ludzi nie jest świadomych tych niebezpieczeństw, co skutkuje zażywaniem tych substancji bez odpowiedzialności i rozwagi.\n\nInterwencja policji w takich sytuacjach jest często ostatnią deską ratunku dla osób, które straciły kontrolę nad swoim zachowaniem pod wpływem środków odurzających. Funkcjonariusze muszą podejmować szybkie i często trudne decyzje, aby zapobiec dalszym zagrożeniom zarówno dla osoby pod wpływem substancji, jak i dla innych ludzi w pobliżu. Należy pamiętać, że ich celem jest zapewnienie bezpieczeństwa i ochrona zdrowia publicznego.\n\nWśród społeczeństwa rośnie świadomość niebezpieczeństw związanych z dopalaczami, jednak wciąż wiele pozostaje do zrobienia w kierunku profilaktyki i edukacji. Szkoły, rodziny i instytucje publiczne powinny współpracować, aby informować młodych ludzi o ryzyku związanym z zażywaniem środków odurzających i promować zdrowy styl życia.\n\nŚmierć 28-latka w Katowicach jest bolesnym przypomnieniem o konieczności podjęcia zdecydowanych kroków w walce z handlem i zażywaniem dopalaczy. Władze powinny kontynuowaćwalkę z przestępczością związaną z substancjami psychoaktywnymi, jednocześnie zapewniając wsparcie dla osób uzależnionych i ich rodzin. Tylko poprzez wspólne działania możemy ograniczyć liczbę tragicznych zdarzeń i tworzyć społeczeństwo bardziej świadome i bezpieczne.", "Model": "@cf/meta/llama-3.3-70b-instruct-fp8-fast"}