{"ID": 2361, "Provider": "tvn24", "URL": "https://tvn24.pl/polska/ipn-i-msz-odpowiadaja-wladimirowi-putinowi-ws-pakt-ribbentrop-molotow-ra995097-ls2614592", "Zdarzenie": "Oświadczenie polskiego MSZ oraz IPN w odpowiedzi na wypowiedzi Władimira Putina dotyczące przyczyn wybuchu II wojny światowej.", "Temat": "Spór historyczno-dyplomatyczny między Polską a Rosją.", "Długość": "Długi artykuł informacyjno-publicystyczny.", "Wygenerowany tytuł": "Spór historyczno-dyplomatyczny między Polską a Rosją: Odpowiedź na wypowiedzi Władimira Putina\n\n", "Wygenerowany tekst": " W ostatnich dniach światowe media obiegła wiadomość o ostrych wypowiedziach Władimira Putina, prezydenta Rosji, dotyczących przyczyn wybuchu II wojny światowej. Jego słowa wywołały falę krytyki i sprzeciwu w Polsce, a także w innych krajach Europy. W odpowiedzi na te wypowiedzi polskie Ministerstwo Spraw Zagranicznych oraz Instytut Pamięci Narodowej wydały oświadczenia, w których stanowczo zaprotestowano przeciwko manipulowaniu historią i próbom fałszywego przedstawienia przyczyn wybuchu wojny.\n\nSpór historyczno-dyplomatyczny między Polską a Rosją ma długą historię i sięga lat powojennych. Jednakże, ostatnie wypowiedzi Putina wydają się być nowym etapem w tym sporze. Prezydent Rosji stwierdził, że Polska ponosi winę za wybuch II wojny światowej, powołując się na układ Ribbentrop-Mołotow z 1939 roku, w którym Niemcy i Związek Radziecki ustaliły granice swoich wpływów w Europie Środkowo-Wschodniej. Putin twierdzi, że Polska miała możliwość przeciwstawienia się układowi, lecz jej władze nie zdecydowały się na to.\n\nOświadczenie polskiego MSZ stanowczo zaprzecza tym twierdzeniom, wskazując na fakt, że Polska była pierwszym krajem, który został zaatakowany przez Niemcy w 1939 roku, co doprowadziło do wybuchu II wojny światowej. Ministerstwo podkreśla, że polska armia stawiała opór agresorowi, a także że Polska była świadoma zagrożenia ze strony Związku Radzieckiego i Niemiec. Instytut Pamięci Narodowej w swoim oświadczeniu podkreśla, że wypowiedzi Putina są próbą zafałszowania historii i usprawiedliwienia agresji Związku Radzieckiego wobec Polski w 1939 roku.\n\nSpór historyczno-dyplomatyczny między Polską a Rosją nie ogranicza się tylko do kwestii II wojny światowej. Jest on także wyrazem głębszych różnic w podejściu do historii i polityki między oboma krajami. Polska, jako kraj, który przez wieki był poddany wpływom obcych mocarstw, jest szczególnie wrażliwa na kwestie suwerenności i integralności terytorialnej. Rosja, z kolei, ma ambicje grandiacyjne i dąży do odbudowy swojej pozycji jako jednego z głównych graczy na arenie międzynarodowej.\n\nW tym kontekście spór o II wojnę światową jest tylko jednym z elementów szerszego sporu o przyszłość Europy irolę Rosji w niej. Polska, jako członek Unii Europejskiej i NATO, opowiada się za umacnianiem integracji europejskiej i utrzymaniem sojuszy transatlantyckich. Rosja, z kolei, dąży do osłabienia tych instytucji i utworzenia nowego ładu międzynarodowego, w którym będzie odgrywała kluczową rolę.\n\nW związku z tym, spór historyczno-dyplomatyczny między Polską a Rosją nie może być traktowany wyłącznie jako spór o historię. Jest on także wyrazem walki o przyszłość Europy i rolę Rosji w niej. Polska i inne kraje Europy powinny być świadome tej groźby i powinny podejmować działania, które będą umacniały integrację europejską i sojusze transatlantyckie, a także będą zdecydowanie przeciwstawiały się fałszywym narracjom historycznym i próbom manipulowania opinią publiczną.", "Model": "@cf/meta/llama-3.3-70b-instruct-fp8-fast"}