{"ID": 750, "Provider": "businessinsider", "URL": "https://businessinsider.com.pl/finanse/kara-na-getback-od-knf/kx76zjg", "Zdarzenie": "Nałożenie przez KNF kary finansowej na spółkę GetBack za nieprawidłowości w raportach okresowych.", "Temat": "Afera finansowa i nadzór nad rynkiem kapitałowym.", "Długość": "Średniej długości artykuł informacyjny.", "Wygenerowany tytuł": "Kara finansowa dla GetBack -effects afera finansowa i nadzór nad rynkiem kapitałowym\n\n", "Wygenerowany tekst": " Komisja Nadzoru Finansowego (KNF) nałożyła karę finansową na spółkę GetBack za nieprawidłowości w raportach okresowych. To ważny sygnał, że nadzór nad rynkiem kapitałowym w Polsce jest zaangażowany w walkedzenie prawidłowości funkcjonowania podmiotów giełdowych. Afera wokół GetBack ujawniła wiele nieprawidłowości w raportowaniu finansowym, co może mieć konsekwencje dla wiarygodności całego rynku kapitałowego.\n\nGetBack, spółka specjalizująca się w windykacji wierzytelności, od kilku latbx budziła wątpliwości inwestorów i analityków. Nieprawidłowości w raportach finansowych dotyczyły m.in. błędnego ustalania wartości aktywów i zaniżania strat. KNF przeprowadziła szczegółowe postępowanie wyjaśniające, które potwierdziło te nieprawidłowości.\n\nNałożona kara finansowa to tylko jeden z elementów działań regulatora, którymidt może podjąć w celu przywrócenia porządku na rynku kapitałowym. Bardziej istotny może być wpływ tej decyzji na przyszłą działalność GetBack i wiarygodność spółek notowanych na GPW.\n\nPowyższe zdarzenie potwierdza, że w Polsce istnieje sprawny system nadzoru, który jest w stanie szybko reagować na nieprawidłowości na rynku kapitałowym. Dzięki temu inwestorzy mogą czuć się bezpieczniej, wiedząc, że ich interesy są chronione przez odpowiednie organy nadzorcze. Ważne, aby KNF kontynuowała swoje działania i nie niższała czujności, tak aby kolejne afery finansowe mogły być wykryte i rozwiązane na wczesnym etapie.", "Model": "@cf/meta/llama-3.3-70b-instruct-fp8-fast"}