{"ID": 889, "Provider": "businessinsider", "URL": "https://businessinsider.com.pl/gielda/wiadomosci/afera-getback-i-rola-gpw-kontrola-nik/zxmq1zw", "Zdarzenie": "Kontrola NIK dotycząca nadzoru GPW nad spółką GetBack.", "Temat": "Afera finansowa i odpowiedzialność instytucji państwowych.", "Długość": "Średniej długości artykuł publicystyczny.", "Wygenerowany tytuł": "Kontrola NIK ujawnia braki w nadzorze GPW nad GetBack - kto poniesie odpowiedzialność?\n\n", "Wygenerowany tekst": " Najnowsza kontrola przeprowadzona przez Najwyższą Izbę Kontroli (NIK) dotycząca nadzoru Giełdy Papierów Wartościowych (GPW) nad spółką GetBack ujawniła liczne braki i zaniedbania w tej sprawie. Afera finansowa związana z upadkiem GetBack, spółki zajmującej się zarządzaniem wierzytelnościami, była jednym z największych kryzysów finansowych w ostatnich latach w Polsce. Kontrola NIK pokazała, że GPW nie wykonała należycie swoich obowiązków nadzorczych, co mogło przyczynić się do eskalacji problemów w GetBack.\n\nKontrola NIK jest kolejnym elementem w śledztwie dotyczącym upadku GetBack. Przypomnijmy, że GetBack vertically pod koniec 2018 roku, pozostawiając po sobie Hawa długu wynoszącego kilka miliardów złotych. Upadek spółki wywołał szok na rynku finansowym i ekonomicznym w Polsce, oraz negatywnie wpłynął na zwykłych inwestorów, którzy zainwestowali swoje oszczędności w papiery wartościowe emitowane przez GetBack.\n\nNIK stwierdziła, że GPW nie przeprowadziła wystarczających kontroli i audytów w GetBack, pomimo że spółka ta przejawiała symptomy problemów finansowych. GPW winna była także niewystarczająco reagować na sygnały ostrzegawcze, takie jak nietransparentne operacje finansowe. To zaniechanie mogło umożliwić kontynuowanie przez GetBack ryzykownych działań, co w konsekwencji przyczyniło się do jej upadku.\n\nOdkrycia NIK podnoszą poważne pytania o skuteczność i efektywność instytucji państwowych odpowiedzialnych za nadzór nad rynkiem finansowym. Czy GPW, jako jeden z głównych regulatorów rynku, wykonuje swoje obowiązki w sposób należyty? Czy Komisja Nadzoru Finansowego (KNF) oraz inne instytucje państwowe odpowiednio monitorują sytuację na rynku i reagują na potencjalne zagrożenia?\n\nW świetle ujawnionych przez NIK ustaleń, trudno nie zauważyć, że doszło do wielu zaniechań i luk w systemie nadzoru finansowego. Konieczne jest więc podjęcie zdecydowanych kroków w celu poprawy skuteczności nadzoru oraz zapobiegania podobnym aferom w przyszłości. Oczywiście, konieczne będzie także przeprowadzenie pełnego śledztwa i pociągnięcie do odpowiedzialności wszystkich osób odpowiedzialnych za nieprawidłowości w GetBack, w tym także przedstawicieli instytucji państwowych, którzy zaniedbali swoje obowiązki.\n\nPodsumowując, odkrycia NIK w sprawie GetBack ujawniają poważne słabości w systemie nadzoru finansowego w Polsce. Wyraźnie pokazują one, że instytucje państwowe muszą znacznie poprawić swoje działania, aby zapewnić bezpieczeństwo i stabilność rynku finansowego. Tylko w ten sposób będziemy mogli uniknąć podobnych afer finansowych w przyszłości i chronić oszczędności tysięcy Polaków.", "Model": "@cf/meta/llama-3.3-70b-instruct-fp8-fast"}